ex3/add_sub/add_sub.v
module add_sub(a,b,in_c,out_c,overflow,zero,s);
    input [3:0]a;
    input [3:0]b;
    input in_c;
    output reg out_c,overflow,zero;//overflow判断溢出,zero判断是否全为0
    output reg [3:0] s;
    //reg [3:0] i=0;
    reg [3:0] t_no_Cin;



    always @(a or b or in_c)begin
        zero=0;
        overflow=0;

        t_no_Cin={4{in_c}}^b;//扩展c_in，按位异或B 得到B1(t_no_Cin)
        {out_c,s}=a+{3'b0,in_c}+t_no_Cin;//实现加法器功能
        overflow=(a[3]==t_no_Cin[3])&&(s[3]!=a[3]);//溢出判断
        /*for (i=0;i<=31;i=i+1)begin
            if(s[i]==i[i]) z=1;//判断是否全零，all0,z->1,exist 1,z->0
        end*/
        zero = ~(|s);// |s按位或运算（所有位进行），全0则=0,存在1则=1,～取反，当全0时zero为高电平
    end

endmodule

ex3/add_sub/wave.vcd
$version Generated by VerilatedVcd $end
$timescale 1s $end

 $scope module TOP $end
  $var wire  4 # a [3:0] $end
  $var wire  4 $ b [3:0] $end
  $var wire  1 % in_c $end
  $var wire  1 & out_c $end
  $var wire  1 ' overflow $end
  $var wire  4 ) s [3:0] $end
  $var wire  1 ( zero $end
  $scope module add_sub $end
   $var wire  4 # a [3:0] $end
   $var wire  4 $ b [3:0] $end
   $var wire  1 % in_c $end
   $var wire  1 & out_c $end
   $var wire  1 ' overflow $end
   $var wire  4 ) s [3:0] $end
   $var wire  4 * t_no_Cin [3:0] $end
   $var wire  1 ( zero $end
  $upscope $end
 $upscope $end
$enddefinitions $end


#1
b0000 #
b0000 $
0%
0&
0'
1(
b0000 )
b0000 *
#2
b0001 $
0(
b0001 )
b0001 *
#3
b0001 #
b0000 $
b0000 *
#4
b0001 $
b0010 )
b0001 *
#5
b0000 #
b0000 $
1%
1&
1(
b0000 )
b1111 *
#6
b0001 $
0&
0(
b1111 )
b1110 *
#7
b0001 #
b0000 $
1&
b0001 )
b1111 *
#8
b0001 $
1(
b0000 )
b1110 *
