ex2/encode42/encode42.v
module encode42(x,en,y);
    input [3:0] x;
    input en;
    output reg [1:0] y;
    integer i;
    always @(x or en) begin
        if (en) begin
            y = 0;
            for (i=0;i<=3;i=i+1)
                if(x[i] == 1) y = i[1:0];
        end
        else y = 0;
    end
endmodule

ex2/encode42/dump.vcd
$version Generated by VerilatedVcd $end
$timescale 1s $end

 $scope module TOP $end
  $var wire  1 $ en $end
  $var wire  4 # x [3:0] $end
  $var wire  2 % y [1:0] $end
  $scope module encode42 $end
   $var wire  1 $ en $end
   $var wire 32 & i [31:0] $end
   $var wire  4 # x [3:0] $end
   $var wire  2 % y [1:0] $end
  $upscope $end
 $upscope $end
$enddefinitions $end


#1
b0000 #
0$
b00 %
b00000000000000000000000000000000 &
#2
b0001 #
#3
b0011 #
#4
b0111 #
#5
b1111 #
#6
b0000 #
1$
b00000000000000000000000000000100 &
#7
b0001 #
#8
b0011 #
b01 %
#9
b0111 #
b10 %
#10
b1111 #
b11 %
