ex3/ad/half_adder.v
module half_adder(a,b,s,c);
	input a;
	input b;
	output reg s,c;

	always@(a or b)begin
	s = a ^ b ;
	c = a & b;
	end
endmodule

ex3/ad/full_adder.v
module full_adder(a,b,in_c,out_s,out_c);
    input a;
    input b;
    input in_c;
    output reg out_s,out_c;

    wire s1,c1,c2;

    //实例化

    half_adder h1(
    .a(a),
    .b(b),
    .c(c1),
    .s(s1)
    );
    
    half_adder h2(
    .a(in_c),
    .b(s1),
    .c(c2),
    .s(out_s)
    );

    assign out_c = c2 || c1;
endmodule

ex3/ad/wave.vcd
$version Generated by VerilatedVcd $end
$timescale 1s $end

 $scope module TOP $end
  $var wire  1 # a $end
  $var wire  1 $ b $end
  $var wire  1 % in_c $end
  $var wire  1 ' out_c $end
  $var wire  1 & out_s $end
  $scope module full_adder $end
   $var wire  1 # a $end
   $var wire  1 $ b $end
   $var wire  1 ) c1 $end
   $var wire  1 * c2 $end
   $var wire  1 % in_c $end
   $var wire  1 ' out_c $end
   $var wire  1 & out_s $end
   $var wire  1 ( s1 $end
   $scope module h1 $end
    $var wire  1 # a $end
    $var wire  1 $ b $end
    $var wire  1 ) c $end
    $var wire  1 ( s $end
   $upscope $end
   $scope module h2 $end
    $var wire  1 % a $end
    $var wire  1 ( b $end
    $var wire  1 * c $end
    $var wire  1 & s $end
   $upscope $end
  $upscope $end
 $upscope $end
$enddefinitions $end


#1
0#
0$
0%
0&
0'
0(
0)
0*
#2
1$
1&
1(
#3
1#
0$
#4
1$
0&
1'
0(
1)
#5
0#
0$
1%
1&
0'
0)
#6
1$
0&
1'
1(
1*
#7
1#
0$
#8
1$
1&
0(
1)
0*
